win_env/__init__.py
win_env/__main__.py
win_env/env.py
win_all_env-1.1.3.dist-info/LICENSE
win_all_env-1.1.3.dist-info/METADATA
win_all_env-1.1.3.dist-info/WHEEL
win_all_env-1.1.3.dist-info/entry_points.txt
win_all_env-1.1.3.dist-info/top_level.txt
win_all_env-1.1.3.dist-info/RECORD
