Metadata-Version: 2.1
Name: win_all_env
Version: 1.1.3
Summary: windows env
Home-page: https://github.com/akino11/win_env
Author: ookatuk
Author-email: okatuhumi@gmail.com
Keywords: win-env
Requires-Python: >=3.12.3
License-File: LICENSE
